CHANGELOG.txt
LICENSE.txt
MANIFEST.in
README.txt
setup.py
MultiDownload/__init__.py
MultiDownload.egg-info/PKG-INFO
MultiDownload.egg-info/SOURCES.txt
MultiDownload.egg-info/dependency_links.txt
MultiDownload.egg-info/requires.txt
MultiDownload.egg-info/top_level.txt